<Properties GitUserInfo="UsingGIT" StartupConfiguration="{FA944A2F-D6E6-4D73-9AAA-A9FCC0984FD6}|Default">
  <MonoDevelop.Ide.Workbench>
    <Files>
      <File FileName="FileStorageManager/Controllers/AccountController.cs" Line="45" Column="86" />
      <File FileName="FileStorageManager/Startup.cs" Line="56" Column="1" />
    </Files>
    <Pads>
      <Pad Id="ProjectPad">
        <State name="__root__">
          <Node name="FileStorageManager" expanded="True">
            <Node name="FileStorageManager" expanded="True">
              <Node name="Controllers" expanded="True">
                <Node name="AccountController.cs" selected="True" />
              </Node>
              <Node name="Data" expanded="True">
                <Node name="Migrations" expanded="True">
                  <Node name="IdentityServer" expanded="True">
                    <Node name="PersistedGrantDb" expanded="True" />
                  </Node>
                </Node>
              </Node>
              <Node name="Migrations" expanded="True" />
              <Node name="Models" expanded="True">
                <Node name="Account" expanded="True" />
              </Node>
              <Node name="Properties" expanded="True" />
              <Node name="Views" expanded="True">
                <Node name="Shared" expanded="True" />
              </Node>
            </Node>
          </Node>
        </State>
      </Pad>
    </Pads>
  </MonoDevelop.Ide.Workbench>
  <MonoDevelop.Ide.DebuggingService.PinnedWatches />
  <MonoDevelop.Ide.Workspace ActiveConfiguration="Debug" />
  <MonoDevelop.Ide.ItemProperties.FileStorageManager PreferredExecutionTarget="/Applications/Safari.app" />
  <MonoDevelop.Ide.DebuggingService.Breakpoints>
    <BreakpointStore />
  </MonoDevelop.Ide.DebuggingService.Breakpoints>
  <MultiItemStartupConfigurations />
</Properties>